sdf4sim
