Metadata-Version: 1.1
Name: sdf4sim
Version: 0.5.0
Summary: A package which demostrates the use of SDF as the model of computation for a non-iterative co-simulation.
Home-page: https://github.com/sglumac/sdf4sim
Author: Slaven Glumac
Author-email: slaven.glumac@gmail.com
License: MIT license
Keywords: sdf4sim
Platform: UNKNOWN
Classifier: Development Status :: 2 - Pre-Alpha
Classifier: Intended Audience :: Developers
Classifier: License :: OSI Approved :: MIT License
Classifier: Natural Language :: English
Classifier: Programming Language :: Python :: 3
Classifier: Programming Language :: Python :: 3.7
